{
  "question": "The music of the late ’70s is often described as _________ , despite the notable exception of a few innovators in the budding punk and hip-hop scenes.\nA. derivative\nB. trite\nC. inspired\nD. visionary\nE. enigmatic\nF. cerebral\nShow\nHide\nAnswer\n_________________\nGRE Prep WhatsApp Community -\nJOIN US\n!!\nGRE PREMIUM Quant Question Banks - Topic-Wise 2700 Questions\nHow to achieve your target GRE score on a budget!!!\nGRE Hard and Tricky\nVERBAL\nPractice: NEW Questions Daily 2025\n!!\nGRE-Skill Builder Project II Ed.2025 DAILY\nQUANT\nQUESTIONS TO PRACTICE\n!!\nThe Best GRE Books of 2025\n!!\nSignature Read More",
  "answer_choices": [],
  "correct_answer": "d",
  "explanation": "",
  "question_type": "Unknown",
  "source_url": "https://gre.myprepclub.com/forum/qotd-9-the-music-of-the-late-70s-is-often-described-as-2185.html",
  "main_category": "Verbal Section",
  "category": "Sentence Equivalence"
}