{
  "question": "This question is part of 5 lb. Book of GRE® Practice Problems Verbal Question Directory\nAlthough accommodating in person, George Orwell _________ defended his political positions in print.\nA.\ttenaciously\nB.\tobsequiously\nC.\tinadvertently\nD.\tdoggedly\nE.\tsycophantically\nF.\tidiosyncratically\nPractice Questions\nQuestion: 22\nPage: 101\nShow\nHide\nAnswer\n_________________\nSandy\nIf you found this post useful, please let me know by pressing the Kudos Button\nTry our free Online GRE Test\nSignature Read More",
  "answer_choices": [],
  "correct_answer": "d",
  "explanation": "",
  "question_type": "Unknown",
  "source_url": "https://gre.myprepclub.com/forum/although-accommodating-in-person-george-orwell-7061.html",
  "main_category": "Verbal Section",
  "category": "Sentence Equivalence"
}