{
  "question": "This question is part of 5 lb. Book of GRE® Practice Problems Verbal Question Directory\nAlthough historically, paints were often tinted with toxic elements such as lead, cadmium, and mercury, _________ number of painters lived to be seventy, eighty, and even ninety.\nA.\tan incomprehensible\nB.\ta flabbergasting\nC.\tan impossible\nD.\ta confounding\nE.\ta dismaying\nF.\tan enlightening\nPractice Questions\nQuestion: 23\nPage: 101\nShow\nHide\nAnswer\n_________________\nSandy\nIf you found this post useful, please let me know by pressing the Kudos Button\nTry our free Online GRE Test\nSignature Read More",
  "answer_choices": [],
  "correct_answer": "d",
  "explanation": "",
  "question_type": "Unknown",
  "source_url": "https://gre.myprepclub.com/forum/although-historically-paints-were-often-tinted-with-toxic-7062.html",
  "main_category": "Verbal Section",
  "category": "Sentence Equivalence"
}