{
  "question": "One does not generally associate teenagers with (i) ________. Jean, however, exercises a self-discipline that verges on (ii) ________. It is unclear whether this is a testament to a particularly conservative upbringing or a reaction against an excessively (iii) ________ one.\nBlank (i)\nBlank (ii)\nBlank (iii)\nA. silent obedience\nD. asperity\nG. illiberal\nB. polished urbanity\nE. punishment\nH. permissive\nC. practiced restrain\nF. asceticism\nI. meddlesome\nShow\nHide\nAnswer\n_________________\nGRE Prep WhatsApp Community -\nJOIN US\n!!\nGRE PREMIUM Quant Question Banks - Topic-Wise 2700 Questions\nHow to achieve your target GRE score on a budget!!!\nGRE Hard and Tricky\nVERBAL\nPractice: NEW Questions Daily 2025\n!!\nGRE-Skill Builder Project II Ed.2025 DAILY\nQUANT\nQUESTIONS TO PRACTICE\n!!\nThe Best GRE Books of 2025\n!!\nSignature Read More",
  "answer_choices": [],
  "correct_answer": "d",
  "explanation": "",
  "question_type": "Text Completion",
  "source_url": "https://gre.myprepclub.com/forum/one-does-not-generally-associate-teenagers-with-i-jean-ho-35046.html",
  "main_category": "Verbal Section",
  "category": "Text Completion"
}